evolab/__init__.py
evolab/misc/__init__.py
evolab/misc/main.py
evolab-0.0.1.dist-info/METADATA
evolab-0.0.1.dist-info/WHEEL
evolab-0.0.1.dist-info/entry_points.txt
evolab-0.0.1.dist-info/licenses/LICENSE.txt
evolab-0.0.1.dist-info/RECORD
